README.md
setup.cfg
setup.py
cli/__init__.py
cli/cli.py
richwx.egg-info/PKG-INFO
richwx.egg-info/SOURCES.txt
richwx.egg-info/dependency_links.txt
richwx.egg-info/entry_points.txt
richwx.egg-info/requires.txt
richwx.egg-info/top_level.txt