Metadata-Version: 2.1
Name: richwx
Version: 0.0.3
Summary: UNKNOWN
Home-page: https://github.com/WxBDM/richwx
Author: Brandon Molyneaux
License: apache-2.0
Download-URL: https://github.com/WxBDM/richwx/archive/refs/tags/v0.0.3.tar.gz
Platform: UNKNOWN
Classifier: Development Status :: 3 - Alpha
Classifier: Intended Audience :: Developers
Classifier: Topic :: Software Development :: Build Tools
Classifier: License :: OSI Approved :: Apache Software License
Classifier: Programming Language :: Python :: 3.8
Classifier: Programming Language :: Python :: 3.9
Classifier: Programming Language :: Python :: 3.10
Requires-Python: >=3.8
